lmdb_dataset/__init__.py
lmdb_dataset/concat.py
lmdb_dataset/dataset.py
lmdb_dataset/keyed_dataset.py
lmdb_dataset/keyed_writer.py
lmdb_dataset/utils.py
lmdb_dataset/writer.py
lmdb_dataset-0.0.1.dist-info/LICENSE.txt
lmdb_dataset-0.0.1.dist-info/METADATA
lmdb_dataset-0.0.1.dist-info/WHEEL
lmdb_dataset-0.0.1.dist-info/top_level.txt
lmdb_dataset-0.0.1.dist-info/RECORD
